BridgeAccesslib/__init__.py
BridgeAccesslib/comm.py
BridgeAccesslib/comm_dummy.py
BridgeAccesslib/extended_comm.py
BridgeAccesslib/data_convert/__init__.py
BridgeAccesslib/data_convert/chip_bitmap_pos.py
BridgeAccesslib/data_convert/data_swap.py
DDBridgeAccesslibDummy-0.1.1.dist-info/METADATA
DDBridgeAccesslibDummy-0.1.1.dist-info/WHEEL
DDBridgeAccesslibDummy-0.1.1.dist-info/top_level.txt
DDBridgeAccesslibDummy-0.1.1.dist-info/RECORD
