Metadata-Version: 2.1
Name: DDBridgeAccesslibDummy
Version: 0.1.1
Summary: This lib controls library for pothonai project
Home-page: UNKNOWN
License: CC0 1.0 Universal
Platform: UNKNOWN
Classifier: Development Status :: 4 - Beta
Classifier: Programming Language :: Python :: 3
Requires-Python: >=3
Requires-Dist: numpy (==1.23.4)
